profilehooks.py
profilehooks-1.11.2.dist-info/LICENSE
profilehooks-1.11.2.dist-info/METADATA
profilehooks-1.11.2.dist-info/WHEEL
profilehooks-1.11.2.dist-info/top_level.txt
profilehooks-1.11.2.dist-info/RECORD
