Metadata-Version: 1.1
Name: profilehooks
Version: 1.11.2
Summary: Decorators for profiling/timing/tracing individual functions
Home-page: https://mg.pov.lt/profilehooks/
Author: Marius Gedminas
Author-email: marius@gedmin.as
License: MIT
Keywords: profile coverage decorators
Platform: UNKNOWN
Classifier: Development Status :: 5 - Production/Stable
Classifier: Environment :: Console
Classifier: Intended Audience :: Developers
Classifier: License :: OSI Approved :: MIT License
Classifier: Programming Language :: Python
Classifier: Operating System :: OS Independent
Classifier: Programming Language :: Python :: 2.7
Classifier: Programming Language :: Python :: 3.5
Classifier: Programming Language :: Python :: 3.6
Classifier: Programming Language :: Python :: 3.7
Classifier: Programming Language :: Python :: 3.8
Classifier: Programming Language :: Python :: Implementation :: CPython
Classifier: Programming Language :: Python :: Implementation :: PyPy
